frontmatter/__init__.py
frontmatter-3.0.7.dist-info/LICENSE
frontmatter-3.0.7.dist-info/METADATA
frontmatter-3.0.7.dist-info/WHEEL
frontmatter-3.0.7.dist-info/top_level.txt
frontmatter-3.0.7.dist-info/RECORD
