Metadata-Version: 2.1
Name: frontmatter
Version: 3.0.7
Summary: Extract YAML frontmatter from files and strings.
Home-page: https://github.com/jonbeebe/frontmatter
Author: Jonathan Beebe
Author-email: me@jonbeebe.net
License: UNKNOWN
Keywords: yaml frontmatter front-matter markdown blogging
Platform: UNKNOWN
Classifier: Development Status :: 5 - Production/Stable
Classifier: Intended Audience :: Developers
Classifier: Topic :: Software Development :: Libraries :: Python Modules
Classifier: License :: OSI Approved :: ISC License (ISCL)
Classifier: Programming Language :: Python :: 2.7
Classifier: Programming Language :: Python :: 3
Classifier: Programming Language :: Python :: 3.4
Classifier: Programming Language :: Python :: 3.5
Classifier: Programming Language :: Python :: 3.6
Classifier: Programming Language :: Python :: 3.7
